category_encoders/__init__.py
category_encoders/backward_difference.py
category_encoders/basen.py
category_encoders/binary.py
category_encoders/cat_boost.py
category_encoders/count.py
category_encoders/glmm.py
category_encoders/hashing.py
category_encoders/helmert.py
category_encoders/james_stein.py
category_encoders/leave_one_out.py
category_encoders/m_estimate.py
category_encoders/one_hot.py
category_encoders/ordinal.py
category_encoders/polynomial.py
category_encoders/sum_coding.py
category_encoders/target_encoder.py
category_encoders/utils.py
category_encoders/woe.py
category_encoders/wrapper.py
examples/__init__.py
examples/column_transformer_example.py
examples/encoding_examples.py
examples/grid_search_example.py
examples/benchmarking/__init__.py
examples/benchmarking/benchmarking.py
examples/benchmarking/reporting.py
examples/source_data/__init__.py
examples/source_data/loaders.py
category_encoders_dev-2.2.2.post2021.dist-info/LICENSE.md
category_encoders_dev-2.2.2.post2021.dist-info/METADATA
category_encoders_dev-2.2.2.post2021.dist-info/WHEEL
category_encoders_dev-2.2.2.post2021.dist-info/top_level.txt
category_encoders_dev-2.2.2.post2021.dist-info/RECORD
