Metadata-Version: 2.1
Name: category-encoders-dev
Version: 2.2.2.post2021
Summary: A collection sklearn transformers to encode categorical variables as numeric
Home-page: https://github.com/scikit-learn-contrib/category_encoders
Author: Will McGinnis
Author-email: will@pedalwrencher.com
License: BSD
Download-URL: https://github.com/scikit-learn-contrib/category_encoders/tarball/2.2.2-2021
Keywords: python data science machine learning pandas sklearn
Platform: UNKNOWN
Classifier: Development Status :: 3 - Alpha
Classifier: Intended Audience :: Developers
Classifier: Programming Language :: Python :: 3
Requires-Dist: numpy (>=1.14.0)
Requires-Dist: scikit-learn (>=0.20.0)
Requires-Dist: scipy (>=1.0.0)
Requires-Dist: statsmodels (>=0.9.0)
Requires-Dist: pandas (>=0.21.1)
Requires-Dist: patsy (>=0.5.1)
